CHANGES.txt
DEPENDENCES.txt
README.txt
setup.py
src/ng/__init__.py
src/ng.content.annotation.egg-info/PKG-INFO
src/ng.content.annotation.egg-info/SOURCES.txt
src/ng.content.annotation.egg-info/dependency_links.txt
src/ng.content.annotation.egg-info/namespace_packages.txt
src/ng.content.annotation.egg-info/not-zip-safe
src/ng.content.annotation.egg-info/requires.txt
src/ng.content.annotation.egg-info/top_level.txt
src/ng/content/__init__.py
src/ng/content/annotation/__init__.py
src/ng/content/annotation/configure.zcml
src/ng/content/annotation/ng.content.annotation.txt
src/ng/content/annotation/annotationswitcher/__init__.py
src/ng/content/annotation/annotationswitcher/annotationswitcher.txt
src/ng/content/annotation/annotationswitcher/configure.zcml
src/ng/content/annotation/annotationswitcher/interfaces.py
src/ng/content/annotation/annotationswitcher/demo/__init__.py
src/ng/content/annotation/annotationswitcher/demo/configure.zcml
src/ng/content/annotation/annotationswitcher/demo/interfaces.py
src/ng/content/annotation/dictannotation/__init__.py
src/ng/content/annotation/dictannotation/configure.zcml
src/ng/content/annotation/dictannotation/dictannotation.py
src/ng/content/annotation/dictannotation/dictannotation.txt
src/ng/content/annotation/dictannotation/dictannotation2titlesubscriber.py
src/ng/content/annotation/dictannotation/dictannotationableadapter.py
src/ng/content/annotation/dictannotation/interfaces.py
src/ng/content/annotation/dictannotation/browser/__init__.py
src/ng/content/annotation/dictannotation/browser/configure.zcml
src/ng/content/annotation/docshortannotation/__init__.py
src/ng/content/annotation/docshortannotation/configure.zcml
src/ng/content/annotation/docshortannotation/docshortannotation.py
src/ng/content/annotation/docshortannotation/docshortannotation.txt
src/ng/content/annotation/docshortannotation/docshortannotation2titlesubscriber.py
src/ng/content/annotation/docshortannotation/docshortannotationableadapter.py
src/ng/content/annotation/docshortannotation/interfaces.py
src/ng/content/annotation/docshortannotation/browser/__init__.py
src/ng/content/annotation/docshortannotation/browser/configure.zcml
src/ng/content/annotation/etc/ng.content.annotation-configure.zcml
src/ng/content/annotation/eventannotation/__init__.py
src/ng/content/annotation/eventannotation/configure.zcml
